xifa/__init__.py
xifa/base.py
xifa/gpcm.py
xifa/grm.py
xifa/mhrm.py
xifa/utils.py
xifa-0.1.12.dist-info/LICENSE
xifa-0.1.12.dist-info/METADATA
xifa-0.1.12.dist-info/WHEEL
xifa-0.1.12.dist-info/top_level.txt
xifa-0.1.12.dist-info/RECORD
