Metadata-Version: 2.1
Name: xifa
Version: 0.1.12
Summary: Accelerated Item Factor Analysis
Home-page: https://github.com/psyphh/xifa
Author: Po-Hsien Huang
Author-email: psyphh@gmail.com
Project-URL: Bug Tracker, https://github.com/psyphh/xifa/issues
Classifier: Programming Language :: Python :: 3
Classifier: License :: OSI Approved :: MIT License
Classifier: Operating System :: OS Independent
Requires-Python: >=3.6
License-File: LICENSE
